nanny/__init__.py
nanny/create_local_merge_branch.py
nanny/create_pr.py
nanny/open_my_prs.py
nanny/settings.py
nanny/settings_global.py
nanny/internal/__init__.py
nanny/internal/branch.py
nanny/internal/jira_task.py
nanny/internal/jira_worklog.py
nanny/internal/pr.py
nanny/internal/pr_build_statuses.py
nanny/internal/pr_comments.py
nanny/internal/pr_labels.py
nanny/internal/pr_milestone.py
nanny/internal/pr_reviews.py
nanny/internal/repo.py
nanny/internal/repo_content.py
nanny_kolenkainc-0.0.1.dist-info/METADATA
nanny_kolenkainc-0.0.1.dist-info/WHEEL
nanny_kolenkainc-0.0.1.dist-info/top_level.txt
nanny_kolenkainc-0.0.1.dist-info/RECORD
