Metadata-Version: 2.1
Name: nanny-kolenkainc
Version: 0.0.1
Summary: A small example package
Home-page: https://github.com/kolenkainc/Nanny
Author: Kolenka Inc
Author-email: dmitry@romashov.tech
License: UNKNOWN
Platform: UNKNOWN
Classifier: Programming Language :: Python :: 3
Classifier: License :: OSI Approved :: MIT License
Classifier: Operating System :: OS Independent
Requires-Python: >=3.6
